{"@t":"2021-05-17T15:19:56.0142674Z","@mt":"{StartMessage} [Timing {TimingId}]","StartMessage":"Booting Umbraco 8.13.0.","TimingId":"da9092e","SourceContext":"Umbraco.Core.Runtime.CoreRuntime","ProcessId":13432,"ProcessName":"w3wp","ThreadId":1,"AppDomainId":2,"AppDomainAppId":"LMW3SVC6ROOT","MachineName":"DESKTOP-41N44RE","Log4NetLevel":"INFO ","HttpRequestNumber":1,"HttpRequestId":"552fc49b-768e-4388-b57c-5c4d42da4a8a"}
{"@t":"2021-05-17T15:19:56.1643489Z","@mt":"Booting site '{HostingSiteName}', app '{HostingApplicationID}', path '{HostingPhysicalPath}', server '{MachineName}'.","HostingSiteName":"umbracoV8.local","HostingApplicationID":"/LM/W3SVC/6/ROOT","HostingPhysicalPath":"D:\\Source\\Umbraco813\\Demo\\Structure.Web\\","MachineName":"DESKTOP-41N44RE","SourceContext":"Umbraco.Core.Runtime.CoreRuntime","ProcessId":13432,"ProcessName":"w3wp","ThreadId":1,"AppDomainId":2,"AppDomainAppId":"LMW3SVC6ROOT","Log4NetLevel":"INFO ","HttpRequestNumber":1,"HttpRequestId":"552fc49b-768e-4388-b57c-5c4d42da4a8a"}
{"@t":"2021-05-17T15:19:56.7014105Z","@mt":"Acquiring.","SourceContext":"Umbraco.Core.Runtime.MainDom","ProcessId":13432,"ProcessName":"w3wp","ThreadId":1,"AppDomainId":2,"AppDomainAppId":"LMW3SVC6ROOT","MachineName":"DESKTOP-41N44RE","Log4NetLevel":"INFO ","HttpRequestNumber":1,"HttpRequestId":"552fc49b-768e-4388-b57c-5c4d42da4a8a"}
{"@t":"2021-05-17T15:19:56.7064113Z","@mt":"Acquired.","SourceContext":"Umbraco.Core.Runtime.MainDom","ProcessId":13432,"ProcessName":"w3wp","ThreadId":1,"AppDomainId":2,"AppDomainAppId":"LMW3SVC6ROOT","MachineName":"DESKTOP-41N44RE","Log4NetLevel":"INFO ","HttpRequestNumber":1,"HttpRequestId":"552fc49b-768e-4388-b57c-5c4d42da4a8a"}
{"@t":"2021-05-17T15:20:13.9041735Z","@mt":"{StartMessage} [Timing {TimingId}]","StartMessage":"Resolving composer types.","TimingId":"32f8aa6","SourceContext":"Umbraco.Core.Runtime.CoreRuntime","ProcessId":13432,"ProcessName":"w3wp","ThreadId":1,"AppDomainId":2,"AppDomainAppId":"LMW3SVC6ROOT","MachineName":"DESKTOP-41N44RE","Log4NetLevel":"INFO ","HttpRequestNumber":1,"HttpRequestId":"552fc49b-768e-4388-b57c-5c4d42da4a8a"}
{"@t":"2021-05-17T15:20:14.0742524Z","@mt":"{EndMessage} ({Duration}ms) [Timing {TimingId}]","EndMessage":"Resolved.","Duration":168,"TimingId":"32f8aa6","SourceContext":"Umbraco.Core.Runtime.CoreRuntime","ProcessId":13432,"ProcessName":"w3wp","ThreadId":1,"AppDomainId":2,"AppDomainAppId":"LMW3SVC6ROOT","MachineName":"DESKTOP-41N44RE","Log4NetLevel":"INFO ","HttpRequestNumber":1,"HttpRequestId":"552fc49b-768e-4388-b57c-5c4d42da4a8a"}
{"@t":"2021-05-17T15:20:19.0942092Z","@mt":"Registered with MainDom, localContentDbExists? {LocalContentDbExists}, localMediaDbExists? {LocalMediaDbExists}","LocalContentDbExists":true,"LocalMediaDbExists":true,"SourceContext":"Umbraco.Web.PublishedCache.NuCache.PublishedSnapshotService","ProcessId":13432,"ProcessName":"w3wp","ThreadId":1,"AppDomainId":2,"AppDomainAppId":"LMW3SVC6ROOT","MachineName":"DESKTOP-41N44RE","Log4NetLevel":"INFO ","HttpRequestNumber":1,"HttpRequestId":"552fc49b-768e-4388-b57c-5c4d42da4a8a"}
{"@t":"2021-05-17T15:20:19.0982055Z","@mt":"Creating the content store, localContentDbExists? {LocalContentDbExists}","LocalContentDbExists":true,"SourceContext":"Umbraco.Web.PublishedCache.NuCache.PublishedSnapshotService","ProcessId":13432,"ProcessName":"w3wp","ThreadId":1,"AppDomainId":2,"AppDomainAppId":"LMW3SVC6ROOT","MachineName":"DESKTOP-41N44RE","Log4NetLevel":"INFO ","HttpRequestNumber":1,"HttpRequestId":"552fc49b-768e-4388-b57c-5c4d42da4a8a"}
{"@t":"2021-05-17T15:20:19.1142024Z","@mt":"Creating the media store, localMediaDbExists? {LocalMediaDbExists}","LocalMediaDbExists":true,"SourceContext":"Umbraco.Web.PublishedCache.NuCache.PublishedSnapshotService","ProcessId":13432,"ProcessName":"w3wp","ThreadId":1,"AppDomainId":2,"AppDomainAppId":"LMW3SVC6ROOT","MachineName":"DESKTOP-41N44RE","Log4NetLevel":"INFO ","HttpRequestNumber":1,"HttpRequestId":"552fc49b-768e-4388-b57c-5c4d42da4a8a"}
{"@t":"2021-05-17T15:20:21.0764153Z","@mt":"{StartMessage} [Timing {TimingId}]","StartMessage":"Loading content from local cache file","TimingId":"39cbb75","SourceContext":"Umbraco.Web.PublishedCache.NuCache.PublishedSnapshotService","ProcessId":13432,"ProcessName":"w3wp","ThreadId":1,"AppDomainId":2,"AppDomainAppId":"LMW3SVC6ROOT","MachineName":"DESKTOP-41N44RE","Log4NetLevel":"INFO ","HttpRequestNumber":1,"HttpRequestId":"552fc49b-768e-4388-b57c-5c4d42da4a8a"}
{"@t":"2021-05-17T15:20:21.1244138Z","@mt":"Tried to load content from the local cache file but it was empty.","SourceContext":"Umbraco.Web.PublishedCache.NuCache.PublishedSnapshotService","ProcessId":13432,"ProcessName":"w3wp","ThreadId":1,"AppDomainId":2,"AppDomainAppId":"LMW3SVC6ROOT","MachineName":"DESKTOP-41N44RE","Log4NetLevel":"INFO ","HttpRequestNumber":1,"HttpRequestId":"552fc49b-768e-4388-b57c-5c4d42da4a8a"}
{"@t":"2021-05-17T15:20:21.1244138Z","@mt":"{EndMessage} ({Duration}ms) [Timing {TimingId}]","EndMessage":"Completed.","Duration":47,"TimingId":"39cbb75","SourceContext":"Umbraco.Web.PublishedCache.NuCache.PublishedSnapshotService","ProcessId":13432,"ProcessName":"w3wp","ThreadId":1,"AppDomainId":2,"AppDomainAppId":"LMW3SVC6ROOT","MachineName":"DESKTOP-41N44RE","Log4NetLevel":"INFO ","HttpRequestNumber":1,"HttpRequestId":"552fc49b-768e-4388-b57c-5c4d42da4a8a"}
{"@t":"2021-05-17T15:20:21.1534150Z","@mt":"Loading content from local db raised warnings, will reload from database.","@l":"Warning","SourceContext":"Umbraco.Web.PublishedCache.NuCache.PublishedSnapshotService","ProcessId":13432,"ProcessName":"w3wp","ThreadId":1,"AppDomainId":2,"AppDomainAppId":"LMW3SVC6ROOT","MachineName":"DESKTOP-41N44RE","Log4NetLevel":"WARN ","HttpRequestNumber":1,"HttpRequestId":"552fc49b-768e-4388-b57c-5c4d42da4a8a"}
{"@t":"2021-05-17T15:20:21.1764211Z","@mt":"{StartMessage} [Timing {TimingId}]","StartMessage":"Loading media from local cache file","TimingId":"5438a9c","SourceContext":"Umbraco.Web.PublishedCache.NuCache.PublishedSnapshotService","ProcessId":13432,"ProcessName":"w3wp","ThreadId":1,"AppDomainId":2,"AppDomainAppId":"LMW3SVC6ROOT","MachineName":"DESKTOP-41N44RE","Log4NetLevel":"INFO ","HttpRequestNumber":1,"HttpRequestId":"552fc49b-768e-4388-b57c-5c4d42da4a8a"}
{"@t":"2021-05-17T15:20:21.1764211Z","@mt":"Tried to load media from the local cache file but it was empty.","SourceContext":"Umbraco.Web.PublishedCache.NuCache.PublishedSnapshotService","ProcessId":13432,"ProcessName":"w3wp","ThreadId":1,"AppDomainId":2,"AppDomainAppId":"LMW3SVC6ROOT","MachineName":"DESKTOP-41N44RE","Log4NetLevel":"INFO ","HttpRequestNumber":1,"HttpRequestId":"552fc49b-768e-4388-b57c-5c4d42da4a8a"}
{"@t":"2021-05-17T15:20:21.1764211Z","@mt":"{EndMessage} ({Duration}ms) [Timing {TimingId}]","EndMessage":"Completed.","Duration":0,"TimingId":"5438a9c","SourceContext":"Umbraco.Web.PublishedCache.NuCache.PublishedSnapshotService","ProcessId":13432,"ProcessName":"w3wp","ThreadId":1,"AppDomainId":2,"AppDomainAppId":"LMW3SVC6ROOT","MachineName":"DESKTOP-41N44RE","Log4NetLevel":"INFO ","HttpRequestNumber":1,"HttpRequestId":"552fc49b-768e-4388-b57c-5c4d42da4a8a"}
{"@t":"2021-05-17T15:20:21.1804137Z","@mt":"Loading media from local db raised warnings, will reload from database.","@l":"Warning","SourceContext":"Umbraco.Web.PublishedCache.NuCache.PublishedSnapshotService","ProcessId":13432,"ProcessName":"w3wp","ThreadId":1,"AppDomainId":2,"AppDomainAppId":"LMW3SVC6ROOT","MachineName":"DESKTOP-41N44RE","Log4NetLevel":"WARN ","HttpRequestNumber":1,"HttpRequestId":"552fc49b-768e-4388-b57c-5c4d42da4a8a"}
{"@t":"2021-05-17T15:20:21.2034199Z","@mt":"{StartMessage} [Timing {TimingId}]","StartMessage":"Loading content from database","TimingId":"26a508a","SourceContext":"Umbraco.Web.PublishedCache.NuCache.PublishedSnapshotService","ProcessId":13432,"ProcessName":"w3wp","ThreadId":1,"AppDomainId":2,"AppDomainAppId":"LMW3SVC6ROOT","MachineName":"DESKTOP-41N44RE","Log4NetLevel":"INFO ","HttpRequestNumber":1,"HttpRequestId":"552fc49b-768e-4388-b57c-5c4d42da4a8a"}
{"@t":"2021-05-17T15:20:21.7960769Z","@mt":"{EndMessage} ({Duration}ms) [Timing {TimingId}]","EndMessage":"Completed.","Duration":592,"TimingId":"26a508a","SourceContext":"Umbraco.Web.PublishedCache.NuCache.PublishedSnapshotService","ProcessId":13432,"ProcessName":"w3wp","ThreadId":1,"AppDomainId":2,"AppDomainAppId":"LMW3SVC6ROOT","MachineName":"DESKTOP-41N44RE","Log4NetLevel":"INFO ","HttpRequestNumber":1,"HttpRequestId":"552fc49b-768e-4388-b57c-5c4d42da4a8a"}
{"@t":"2021-05-17T15:20:21.8040831Z","@mt":"{StartMessage} [Timing {TimingId}]","StartMessage":"Loading media from database","TimingId":"8c8f633","SourceContext":"Umbraco.Web.PublishedCache.NuCache.PublishedSnapshotService","ProcessId":13432,"ProcessName":"w3wp","ThreadId":1,"AppDomainId":2,"AppDomainAppId":"LMW3SVC6ROOT","MachineName":"DESKTOP-41N44RE","Log4NetLevel":"INFO ","HttpRequestNumber":1,"HttpRequestId":"552fc49b-768e-4388-b57c-5c4d42da4a8a"}
{"@t":"2021-05-17T15:20:21.8991575Z","@mt":"{EndMessage} ({Duration}ms) [Timing {TimingId}]","EndMessage":"Completed.","Duration":95,"TimingId":"8c8f633","SourceContext":"Umbraco.Web.PublishedCache.NuCache.PublishedSnapshotService","ProcessId":13432,"ProcessName":"w3wp","ThreadId":1,"AppDomainId":2,"AppDomainAppId":"LMW3SVC6ROOT","MachineName":"DESKTOP-41N44RE","Log4NetLevel":"INFO ","HttpRequestNumber":1,"HttpRequestId":"552fc49b-768e-4388-b57c-5c4d42da4a8a"}
{"@t":"2021-05-17T15:20:22.1511574Z","@mt":"Profiler is VoidProfiler, not profiling (must run debug mode to profile).","SourceContext":"Umbraco.Web.Logging.WebProfilerComponent","ProcessId":13432,"ProcessName":"w3wp","ThreadId":1,"AppDomainId":2,"AppDomainAppId":"LMW3SVC6ROOT","MachineName":"DESKTOP-41N44RE","Log4NetLevel":"INFO ","HttpRequestNumber":1,"HttpRequestId":"552fc49b-768e-4388-b57c-5c4d42da4a8a"}
{"@t":"2021-05-17T15:20:22.5934443Z","@mt":"Initializing Umbraco internal event handlers for cache refreshing.","SourceContext":"Umbraco.Web.Cache.DistributedCacheBinderComponent","ProcessId":13432,"ProcessName":"w3wp","ThreadId":1,"AppDomainId":2,"AppDomainAppId":"LMW3SVC6ROOT","MachineName":"DESKTOP-41N44RE","Log4NetLevel":"INFO ","HttpRequestNumber":1,"HttpRequestId":"552fc49b-768e-4388-b57c-5c4d42da4a8a"}
{"@t":"2021-05-17T15:20:22.8634453Z","@mt":"Adding examine event handlers for {RegisteredIndexers} index providers.","RegisteredIndexers":3,"SourceContext":"Umbraco.Web.Search.ExamineComponent","ProcessId":13432,"ProcessName":"w3wp","ThreadId":1,"AppDomainId":2,"AppDomainAppId":"LMW3SVC6ROOT","MachineName":"DESKTOP-41N44RE","Log4NetLevel":"INFO ","HttpRequestNumber":1,"HttpRequestId":"552fc49b-768e-4388-b57c-5c4d42da4a8a"}
{"@t":"2021-05-17T15:20:22.9384490Z","@mt":"Starting initialize async background thread.","SourceContext":"Umbraco.Web.Search.BackgroundIndexRebuilder","ProcessId":13432,"ProcessName":"w3wp","ThreadId":1,"AppDomainId":2,"AppDomainAppId":"LMW3SVC6ROOT","MachineName":"DESKTOP-41N44RE","Log4NetLevel":"INFO ","HttpRequestNumber":1,"HttpRequestId":"552fc49b-768e-4388-b57c-5c4d42da4a8a"}
{"@t":"2021-05-17T15:20:22.9384490Z","@mt":"{EndMessage} ({Duration}ms) [Timing {TimingId}]","EndMessage":"Booted.","Duration":26979,"TimingId":"da9092e","SourceContext":"Umbraco.Core.Runtime.CoreRuntime","ProcessId":13432,"ProcessName":"w3wp","ThreadId":1,"AppDomainId":2,"AppDomainAppId":"LMW3SVC6ROOT","MachineName":"DESKTOP-41N44RE","Log4NetLevel":"INFO ","HttpRequestNumber":1,"HttpRequestId":"552fc49b-768e-4388-b57c-5c4d42da4a8a"}
{"@t":"2021-05-17T15:20:24.1061777Z","@mt":"New url {Url} detected, re-discovering application url.","Url":"http://umbracov8.local:80/umbraco","SourceContext":"Umbraco.Core.Sync.ApplicationUrlHelper","ProcessId":13432,"ProcessName":"w3wp","ThreadId":11,"AppDomainId":2,"AppDomainAppId":"LMW3SVC6ROOT","MachineName":"DESKTOP-41N44RE","Log4NetLevel":"INFO ","HttpRequestNumber":2,"HttpRequestId":"9af013f8-32b5-4917-8a2a-cb8f49a22dff"}
{"@t":"2021-05-17T15:20:24.1131776Z","@mt":"ApplicationUrl: {UmbracoAppUrl} (UmbracoModule request)","UmbracoAppUrl":"http://umbracov8.local:80/umbraco","SourceContext":"Umbraco.Core.Sync.ApplicationUrlHelper","ProcessId":13432,"ProcessName":"w3wp","ThreadId":11,"AppDomainId":2,"AppDomainAppId":"LMW3SVC6ROOT","MachineName":"DESKTOP-41N44RE","Log4NetLevel":"INFO ","HttpRequestNumber":2,"HttpRequestId":"9af013f8-32b5-4917-8a2a-cb8f49a22dff"}
{"@t":"2021-05-17T15:20:35.4324762Z","@mt":"Umbraco has no content","@l":"Warning","SourceContext":"Umbraco.Web.UmbracoModule","ProcessId":13432,"ProcessName":"w3wp","ThreadId":11,"AppDomainId":2,"AppDomainAppId":"LMW3SVC6ROOT","MachineName":"DESKTOP-41N44RE","Log4NetLevel":"WARN ","HttpRequestNumber":2,"HttpRequestId":"9af013f8-32b5-4917-8a2a-cb8f49a22dff"}
{"@t":"2021-05-17T15:22:47.7729219Z","@mt":"[{EventType}] Event Id: {EventId}, State: {State}","EventType":"Information","EventId":0,"State":"Login attempt succeeded for username admin@ad.com from IP address 127.0.0.1","SourceContext":"Umbraco.Core.Logging.OwinLogger","ProcessId":13432,"ProcessName":"w3wp","ThreadId":23,"AppDomainId":2,"AppDomainAppId":"LMW3SVC6ROOT","MachineName":"DESKTOP-41N44RE","Log4NetLevel":"INFO ","HttpRequestNumber":3,"HttpRequestId":"4689ef19-ddbb-44c8-9c3a-f8ccccd79f20"}
{"@t":"2021-05-17T15:22:47.7739265Z","@mt":"[{EventType}] Event Id: {EventId}, State: {State}","EventType":"Information","EventId":0,"State":"User: admin@ad.com logged in from IP address 127.0.0.1","SourceContext":"Umbraco.Core.Logging.OwinLogger","ProcessId":13432,"ProcessName":"w3wp","ThreadId":23,"AppDomainId":2,"AppDomainAppId":"LMW3SVC6ROOT","MachineName":"DESKTOP-41N44RE","Log4NetLevel":"INFO ","HttpRequestNumber":3,"HttpRequestId":"4689ef19-ddbb-44c8-9c3a-f8ccccd79f20"}
{"@t":"2021-05-17T15:24:32.1746439Z","@mt":"Umbraco has no content","@l":"Warning","SourceContext":"Umbraco.Web.UmbracoModule","ProcessId":13432,"ProcessName":"w3wp","ThreadId":5,"AppDomainId":2,"AppDomainAppId":"LMW3SVC6ROOT","MachineName":"DESKTOP-41N44RE","Log4NetLevel":"WARN ","HttpRequestNumber":4,"HttpRequestId":"9e6bb90e-878b-4e79-a361-bea35371c1da"}
{"@t":"2021-05-17T15:24:32.3196445Z","@mt":"Scheduled health check results:","SourceContext":"Umbraco.Web.HealthCheck.HealthCheckResults","ProcessId":13432,"ProcessName":"w3wp","ThreadId":9,"AppDomainId":2,"AppDomainAppId":"LMW3SVC6ROOT","MachineName":"DESKTOP-41N44RE","Log4NetLevel":"INFO "}
{"@t":"2021-05-17T15:24:32.3206438Z","@mt":"Checks for '{HealthCheckName}' all completed successfully.","HealthCheckName":"Folder & File Permissions","SourceContext":"Umbraco.Web.HealthCheck.HealthCheckResults","ProcessId":13432,"ProcessName":"w3wp","ThreadId":9,"AppDomainId":2,"AppDomainAppId":"LMW3SVC6ROOT","MachineName":"DESKTOP-41N44RE","Log4NetLevel":"INFO "}
{"@t":"2021-05-17T15:24:32.3216521Z","@mt":"Result for {HealthCheckName}: {HealthCheckResult}, Message: '{HealthCheckMessage}'","HealthCheckName":"Folder & File Permissions","HealthCheckResult":"Success","HealthCheckMessage":"All folders have the correct permissions set.","SourceContext":"Umbraco.Web.HealthCheck.HealthCheckResults","ProcessId":13432,"ProcessName":"w3wp","ThreadId":9,"AppDomainId":2,"AppDomainAppId":"LMW3SVC6ROOT","MachineName":"DESKTOP-41N44RE","Log4NetLevel":"INFO "}
{"@t":"2021-05-17T15:24:32.3216521Z","@mt":"Result for {HealthCheckName}: {HealthCheckResult}, Message: '{HealthCheckMessage}'","HealthCheckName":"Folder & File Permissions","HealthCheckResult":"Success","HealthCheckMessage":"All files have the correct permissions set.","SourceContext":"Umbraco.Web.HealthCheck.HealthCheckResults","ProcessId":13432,"ProcessName":"w3wp","ThreadId":9,"AppDomainId":2,"AppDomainAppId":"LMW3SVC6ROOT","MachineName":"DESKTOP-41N44RE","Log4NetLevel":"INFO "}
{"@t":"2021-05-17T15:24:32.3236486Z","@mt":"Checks for '{HealthCheckName}' completed with errors.","@l":"Warning","HealthCheckName":"SMTP Settings","SourceContext":"Umbraco.Web.HealthCheck.HealthCheckResults","ProcessId":13432,"ProcessName":"w3wp","ThreadId":9,"AppDomainId":2,"AppDomainAppId":"LMW3SVC6ROOT","MachineName":"DESKTOP-41N44RE","Log4NetLevel":"WARN "}
{"@t":"2021-05-17T15:24:32.3236486Z","@mt":"Result for {HealthCheckName}: {HealthCheckResult}, Message: '{HealthCheckMessage}'","HealthCheckName":"SMTP Settings","HealthCheckResult":"Error","HealthCheckMessage":"In the Web.config file system.net/mailsettings section, the host is not configured.","SourceContext":"Umbraco.Web.HealthCheck.HealthCheckResults","ProcessId":13432,"ProcessName":"w3wp","ThreadId":9,"AppDomainId":2,"AppDomainAppId":"LMW3SVC6ROOT","MachineName":"DESKTOP-41N44RE","Log4NetLevel":"INFO "}
{"@t":"2021-05-17T15:24:32.3236486Z","@mt":"Checks for '{HealthCheckName}' completed with errors.","@l":"Warning","HealthCheckName":"Macro errors","SourceContext":"Umbraco.Web.HealthCheck.HealthCheckResults","ProcessId":13432,"ProcessName":"w3wp","ThreadId":9,"AppDomainId":2,"AppDomainAppId":"LMW3SVC6ROOT","MachineName":"DESKTOP-41N44RE","Log4NetLevel":"WARN "}
{"@t":"2021-05-17T15:24:32.3236486Z","@mt":"Result for {HealthCheckName}: {HealthCheckResult}, Message: '{HealthCheckMessage}'","HealthCheckName":"Macro errors","HealthCheckResult":"Error","HealthCheckMessage":"MacroErrors are set to 'throw' which will prevent some or all pages in your site from loading completely if there are any errors in macros. Rectifying this will set the value to 'inline'.","SourceContext":"Umbraco.Web.HealthCheck.HealthCheckResults","ProcessId":13432,"ProcessName":"w3wp","ThreadId":9,"AppDomainId":2,"AppDomainAppId":"LMW3SVC6ROOT","MachineName":"DESKTOP-41N44RE","Log4NetLevel":"INFO "}
{"@t":"2021-05-17T15:24:32.3236486Z","@mt":"Checks for '{HealthCheckName}' completed with errors.","@l":"Warning","HealthCheckName":"Notification Email Settings","SourceContext":"Umbraco.Web.HealthCheck.HealthCheckResults","ProcessId":13432,"ProcessName":"w3wp","ThreadId":9,"AppDomainId":2,"AppDomainAppId":"LMW3SVC6ROOT","MachineName":"DESKTOP-41N44RE","Log4NetLevel":"WARN "}
{"@t":"2021-05-17T15:24:32.3236486Z","@mt":"Result for {HealthCheckName}: {HealthCheckResult}, Message: '{HealthCheckMessage}'","HealthCheckName":"Notification Email Settings","HealthCheckResult":"Error","HealthCheckMessage":"Notification email is still set to the default value of <strong>your@email.here</strong>.","SourceContext":"Umbraco.Web.HealthCheck.HealthCheckResults","ProcessId":13432,"ProcessName":"w3wp","ThreadId":9,"AppDomainId":2,"AppDomainAppId":"LMW3SVC6ROOT","MachineName":"DESKTOP-41N44RE","Log4NetLevel":"INFO "}
{"@t":"2021-05-17T15:24:32.3236486Z","@mt":"Checks for '{HealthCheckName}' all completed successfully.","HealthCheckName":"Try Skip IIS Custom Errors","SourceContext":"Umbraco.Web.HealthCheck.HealthCheckResults","ProcessId":13432,"ProcessName":"w3wp","ThreadId":9,"AppDomainId":2,"AppDomainAppId":"LMW3SVC6ROOT","MachineName":"DESKTOP-41N44RE","Log4NetLevel":"INFO "}
{"@t":"2021-05-17T15:24:32.3236486Z","@mt":"Result for {HealthCheckName}: {HealthCheckResult}, Message: '{HealthCheckMessage}'","HealthCheckName":"Try Skip IIS Custom Errors","HealthCheckResult":"Success","HealthCheckMessage":"Try Skip IIS Custom Errors is set to 'true' and you're using IIS version '10.0'.","SourceContext":"Umbraco.Web.HealthCheck.HealthCheckResults","ProcessId":13432,"ProcessName":"w3wp","ThreadId":9,"AppDomainId":2,"AppDomainAppId":"LMW3SVC6ROOT","MachineName":"DESKTOP-41N44RE","Log4NetLevel":"INFO "}
{"@t":"2021-05-17T15:24:32.3236486Z","@mt":"Checks for '{HealthCheckName}' all completed successfully.","HealthCheckName":"Custom Errors","SourceContext":"Umbraco.Web.HealthCheck.HealthCheckResults","ProcessId":13432,"ProcessName":"w3wp","ThreadId":9,"AppDomainId":2,"AppDomainAppId":"LMW3SVC6ROOT","MachineName":"DESKTOP-41N44RE","Log4NetLevel":"INFO "}
{"@t":"2021-05-17T15:24:32.3236486Z","@mt":"Result for {HealthCheckName}: {HealthCheckResult}, Message: '{HealthCheckMessage}'","HealthCheckName":"Custom Errors","HealthCheckResult":"Success","HealthCheckMessage":"Custom errors are set to 'RemoteOnly'.","SourceContext":"Umbraco.Web.HealthCheck.HealthCheckResults","ProcessId":13432,"ProcessName":"w3wp","ThreadId":9,"AppDomainId":2,"AppDomainAppId":"LMW3SVC6ROOT","MachineName":"DESKTOP-41N44RE","Log4NetLevel":"INFO "}
{"@t":"2021-05-17T15:24:32.3236486Z","@mt":"Checks for '{HealthCheckName}' all completed successfully.","HealthCheckName":"Trace Mode","SourceContext":"Umbraco.Web.HealthCheck.HealthCheckResults","ProcessId":13432,"ProcessName":"w3wp","ThreadId":9,"AppDomainId":2,"AppDomainAppId":"LMW3SVC6ROOT","MachineName":"DESKTOP-41N44RE","Log4NetLevel":"INFO "}
{"@t":"2021-05-17T15:24:32.3236486Z","@mt":"Result for {HealthCheckName}: {HealthCheckResult}, Message: '{HealthCheckMessage}'","HealthCheckName":"Trace Mode","HealthCheckResult":"Success","HealthCheckMessage":"Trace mode is disabled.","SourceContext":"Umbraco.Web.HealthCheck.HealthCheckResults","ProcessId":13432,"ProcessName":"w3wp","ThreadId":9,"AppDomainId":2,"AppDomainAppId":"LMW3SVC6ROOT","MachineName":"DESKTOP-41N44RE","Log4NetLevel":"INFO "}
{"@t":"2021-05-17T15:24:32.3236486Z","@mt":"Checks for '{HealthCheckName}' all completed successfully.","HealthCheckName":"Debug Compilation Mode","SourceContext":"Umbraco.Web.HealthCheck.HealthCheckResults","ProcessId":13432,"ProcessName":"w3wp","ThreadId":9,"AppDomainId":2,"AppDomainAppId":"LMW3SVC6ROOT","MachineName":"DESKTOP-41N44RE","Log4NetLevel":"INFO "}
{"@t":"2021-05-17T15:24:32.3236486Z","@mt":"Result for {HealthCheckName}: {HealthCheckResult}, Message: '{HealthCheckMessage}'","HealthCheckName":"Debug Compilation Mode","HealthCheckResult":"Success","HealthCheckMessage":"Debug compilation mode is disabled.","SourceContext":"Umbraco.Web.HealthCheck.HealthCheckResults","ProcessId":13432,"ProcessName":"w3wp","ThreadId":9,"AppDomainId":2,"AppDomainAppId":"LMW3SVC6ROOT","MachineName":"DESKTOP-41N44RE","Log4NetLevel":"INFO "}
{"@t":"2021-05-17T15:24:32.3236486Z","@mt":"Checks for '{HealthCheckName}' completed with errors.","@l":"Warning","HealthCheckName":"Cross-site scripting Protection (X-XSS-Protection header)","SourceContext":"Umbraco.Web.HealthCheck.HealthCheckResults","ProcessId":13432,"ProcessName":"w3wp","ThreadId":9,"AppDomainId":2,"AppDomainAppId":"LMW3SVC6ROOT","MachineName":"DESKTOP-41N44RE","Log4NetLevel":"WARN "}
{"@t":"2021-05-17T15:24:32.3236486Z","@mt":"Result for {HealthCheckName}: {HealthCheckResult}, Message: '{HealthCheckMessage}'","HealthCheckName":"Cross-site scripting Protection (X-XSS-Protection header)","HealthCheckResult":"Error","HealthCheckMessage":"The header <strong>X-XSS-Protection</strong> was not found.","SourceContext":"Umbraco.Web.HealthCheck.HealthCheckResults","ProcessId":13432,"ProcessName":"w3wp","ThreadId":9,"AppDomainId":2,"AppDomainAppId":"LMW3SVC6ROOT","MachineName":"DESKTOP-41N44RE","Log4NetLevel":"INFO "}
{"@t":"2021-05-17T15:24:32.3236486Z","@mt":"Checks for '{HealthCheckName}' completed with errors.","@l":"Warning","HealthCheckName":"Cookie hijacking and protocol downgrade attacks Protection (Strict-Transport-Security Header (HSTS))","SourceContext":"Umbraco.Web.HealthCheck.HealthCheckResults","ProcessId":13432,"ProcessName":"w3wp","ThreadId":9,"AppDomainId":2,"AppDomainAppId":"LMW3SVC6ROOT","MachineName":"DESKTOP-41N44RE","Log4NetLevel":"WARN "}
{"@t":"2021-05-17T15:24:32.3236486Z","@mt":"Result for {HealthCheckName}: {HealthCheckResult}, Message: '{HealthCheckMessage}'","HealthCheckName":"Cookie hijacking and protocol downgrade attacks Protection (Strict-Transport-Security Header (HSTS))","HealthCheckResult":"Error","HealthCheckMessage":"The header <strong>Strict-Transport-Security</strong> was not found.","SourceContext":"Umbraco.Web.HealthCheck.HealthCheckResults","ProcessId":13432,"ProcessName":"w3wp","ThreadId":9,"AppDomainId":2,"AppDomainAppId":"LMW3SVC6ROOT","MachineName":"DESKTOP-41N44RE","Log4NetLevel":"INFO "}
{"@t":"2021-05-17T15:24:32.3236486Z","@mt":"Checks for '{HealthCheckName}' completed with errors.","@l":"Warning","HealthCheckName":"Content/MIME Sniffing Protection","SourceContext":"Umbraco.Web.HealthCheck.HealthCheckResults","ProcessId":13432,"ProcessName":"w3wp","ThreadId":9,"AppDomainId":2,"AppDomainAppId":"LMW3SVC6ROOT","MachineName":"DESKTOP-41N44RE","Log4NetLevel":"WARN "}
{"@t":"2021-05-17T15:24:32.3236486Z","@mt":"Result for {HealthCheckName}: {HealthCheckResult}, Message: '{HealthCheckMessage}'","HealthCheckName":"Content/MIME Sniffing Protection","HealthCheckResult":"Error","HealthCheckMessage":"The header or meta-tag <strong>X-Content-Type-Options</strong> used to protect against MIME sniffing vulnerabilities was not found.","SourceContext":"Umbraco.Web.HealthCheck.HealthCheckResults","ProcessId":13432,"ProcessName":"w3wp","ThreadId":9,"AppDomainId":2,"AppDomainAppId":"LMW3SVC6ROOT","MachineName":"DESKTOP-41N44RE","Log4NetLevel":"INFO "}
{"@t":"2021-05-17T15:24:32.3236486Z","@mt":"Checks for '{HealthCheckName}' all completed successfully.","HealthCheckName":"Excessive Headers","SourceContext":"Umbraco.Web.HealthCheck.HealthCheckResults","ProcessId":13432,"ProcessName":"w3wp","ThreadId":9,"AppDomainId":2,"AppDomainAppId":"LMW3SVC6ROOT","MachineName":"DESKTOP-41N44RE","Log4NetLevel":"INFO "}
{"@t":"2021-05-17T15:24:32.3236486Z","@mt":"Result for {HealthCheckName}: {HealthCheckResult}, Message: '{HealthCheckMessage}'","HealthCheckName":"Excessive Headers","HealthCheckResult":"Success","HealthCheckMessage":"No headers revealing information about the website technology were found.","SourceContext":"Umbraco.Web.HealthCheck.HealthCheckResults","ProcessId":13432,"ProcessName":"w3wp","ThreadId":9,"AppDomainId":2,"AppDomainAppId":"LMW3SVC6ROOT","MachineName":"DESKTOP-41N44RE","Log4NetLevel":"INFO "}
{"@t":"2021-05-17T15:24:32.3236486Z","@mt":"Checks for '{HealthCheckName}' completed with errors.","@l":"Warning","HealthCheckName":"Click-Jacking Protection","SourceContext":"Umbraco.Web.HealthCheck.HealthCheckResults","ProcessId":13432,"ProcessName":"w3wp","ThreadId":9,"AppDomainId":2,"AppDomainAppId":"LMW3SVC6ROOT","MachineName":"DESKTOP-41N44RE","Log4NetLevel":"WARN "}
{"@t":"2021-05-17T15:24:32.3236486Z","@mt":"Result for {HealthCheckName}: {HealthCheckResult}, Message: '{HealthCheckMessage}'","HealthCheckName":"Click-Jacking Protection","HealthCheckResult":"Error","HealthCheckMessage":"The header or meta-tag <strong>X-Frame-Options</strong> used to control whether a site can be IFRAMEd by another was not found.","SourceContext":"Umbraco.Web.HealthCheck.HealthCheckResults","ProcessId":13432,"ProcessName":"w3wp","ThreadId":9,"AppDomainId":2,"AppDomainAppId":"LMW3SVC6ROOT","MachineName":"DESKTOP-41N44RE","Log4NetLevel":"INFO "}
{"@t":"2021-05-17T15:24:32.3236486Z","@mt":"Checks for '{HealthCheckName}' completed with errors.","@l":"Warning","HealthCheckName":"HTTPS Configuration","SourceContext":"Umbraco.Web.HealthCheck.HealthCheckResults","ProcessId":13432,"ProcessName":"w3wp","ThreadId":9,"AppDomainId":2,"AppDomainAppId":"LMW3SVC6ROOT","MachineName":"DESKTOP-41N44RE","Log4NetLevel":"WARN "}
{"@t":"2021-05-17T15:24:32.3236486Z","@mt":"Result for {HealthCheckName}: {HealthCheckResult}, Message: '{HealthCheckMessage}'","HealthCheckName":"HTTPS Configuration","HealthCheckResult":"Error","HealthCheckMessage":"You are currently not viewing the site using the HTTPS scheme.","SourceContext":"Umbraco.Web.HealthCheck.HealthCheckResults","ProcessId":13432,"ProcessName":"w3wp","ThreadId":9,"AppDomainId":2,"AppDomainAppId":"LMW3SVC6ROOT","MachineName":"DESKTOP-41N44RE","Log4NetLevel":"INFO "}
{"@t":"2021-05-17T15:24:32.3236486Z","@mt":"Result for {HealthCheckName}: {HealthCheckResult}, Message: '{HealthCheckMessage}'","HealthCheckName":"HTTPS Configuration","HealthCheckResult":"Info","HealthCheckMessage":"The appSetting 'Umbraco.Core.UseHttps' is set to 'false' in your web.config file. Once you access this site using the HTTPS scheme, that should be set to 'true'.","SourceContext":"Umbraco.Web.HealthCheck.HealthCheckResults","ProcessId":13432,"ProcessName":"w3wp","ThreadId":9,"AppDomainId":2,"AppDomainAppId":"LMW3SVC6ROOT","MachineName":"DESKTOP-41N44RE","Log4NetLevel":"INFO "}
{"@t":"2021-05-17T15:24:32.3236486Z","@mt":"Result for {HealthCheckName}: {HealthCheckResult}, Message: '{HealthCheckMessage}'","HealthCheckName":"HTTPS Configuration","HealthCheckResult":"Error","HealthCheckMessage":"Certificate validation error: 'The underlying connection was closed: Could not establish trust relationship for the SSL/TLS secure channel.'","SourceContext":"Umbraco.Web.HealthCheck.HealthCheckResults","ProcessId":13432,"ProcessName":"w3wp","ThreadId":9,"AppDomainId":2,"AppDomainAppId":"LMW3SVC6ROOT","MachineName":"DESKTOP-41N44RE","Log4NetLevel":"INFO "}
{"@t":"2021-05-17T15:24:32.3236486Z","@mt":"Checks for '{HealthCheckName}' all completed successfully.","HealthCheckName":"Database data integrity check","SourceContext":"Umbraco.Web.HealthCheck.HealthCheckResults","ProcessId":13432,"ProcessName":"w3wp","ThreadId":9,"AppDomainId":2,"AppDomainAppId":"LMW3SVC6ROOT","MachineName":"DESKTOP-41N44RE","Log4NetLevel":"INFO "}
{"@t":"2021-05-17T15:24:32.3236486Z","@mt":"Result for {HealthCheckName}: {HealthCheckResult}, Message: '{HealthCheckMessage}'","HealthCheckName":"Database data integrity check","HealthCheckResult":"Success","HealthCheckMessage":"<p>All document paths are valid</p>\r\n","SourceContext":"Umbraco.Web.HealthCheck.HealthCheckResults","ProcessId":13432,"ProcessName":"w3wp","ThreadId":9,"AppDomainId":2,"AppDomainAppId":"LMW3SVC6ROOT","MachineName":"DESKTOP-41N44RE","Log4NetLevel":"INFO "}
{"@t":"2021-05-17T15:24:32.3236486Z","@mt":"Result for {HealthCheckName}: {HealthCheckResult}, Message: '{HealthCheckMessage}'","HealthCheckName":"Database data integrity check","HealthCheckResult":"Success","HealthCheckMessage":"<p>All media paths are valid</p>\r\n","SourceContext":"Umbraco.Web.HealthCheck.HealthCheckResults","ProcessId":13432,"ProcessName":"w3wp","ThreadId":9,"AppDomainId":2,"AppDomainAppId":"LMW3SVC6ROOT","MachineName":"DESKTOP-41N44RE","Log4NetLevel":"INFO "}
{"@t":"2021-05-17T16:06:16.2697293Z","@mt":"[{EventType}] Event Id: {EventId}, State: {State}","EventType":"Information","EventId":0,"State":"Login attempt succeeded for username admin@ad.com from IP address 127.0.0.1","SourceContext":"Umbraco.Core.Logging.OwinLogger","ProcessId":13432,"ProcessName":"w3wp","ThreadId":68,"AppDomainId":2,"AppDomainAppId":"LMW3SVC6ROOT","MachineName":"DESKTOP-41N44RE","Log4NetLevel":"INFO ","HttpRequestNumber":5,"HttpRequestId":"327ec28a-5b22-4c58-940b-0f7a4a8d8f45"}
{"@t":"2021-05-17T16:06:16.2707148Z","@mt":"[{EventType}] Event Id: {EventId}, State: {State}","EventType":"Information","EventId":0,"State":"User: admin@ad.com logged in from IP address 127.0.0.1","SourceContext":"Umbraco.Core.Logging.OwinLogger","ProcessId":13432,"ProcessName":"w3wp","ThreadId":68,"AppDomainId":2,"AppDomainAppId":"LMW3SVC6ROOT","MachineName":"DESKTOP-41N44RE","Log4NetLevel":"INFO ","HttpRequestNumber":5,"HttpRequestId":"327ec28a-5b22-4c58-940b-0f7a4a8d8f45"}
{"@t":"2021-05-17T16:26:07.7899245Z","@mt":"[{EventType}] Event Id: {EventId}, State: {State}","EventType":"Information","EventId":0,"State":"User logged will be logged out due to timeout: admin@ad.com, IP Address: 127.0.0.1","SourceContext":"Umbraco.Core.Logging.OwinLogger","ProcessId":13432,"ProcessName":"w3wp","ThreadId":69,"AppDomainId":2,"AppDomainAppId":"LMW3SVC6ROOT","MachineName":"DESKTOP-41N44RE","Log4NetLevel":"INFO ","HttpRequestNumber":6,"HttpRequestId":"108b3917-4f10-47a4-a1a7-3f7b3033d75e"}
